anneal.c
main.py
setup.py
mixel.egg-info/PKG-INFO
mixel.egg-info/SOURCES.txt
mixel.egg-info/dependency_links.txt
mixel.egg-info/top_level.txt