Metadata-Version: 1.1
Name: mixel
Version: 0.0.1
Summary: a small python module for recoloring images with pixels from a palette image
Home-page: https://github.com/lpang36/mixel
Author: Lawrence Pang
Author-email: lawrencepang36@gmail.com
License: MIT
Platform: any
Classifier: Programming Language :: Python :: 3
Classifier: Programming Language :: Python :: 2
Classifier: License :: OSI Approved :: MIT License
Classifier: Operating System :: OS Independent
